README.md
setup.cfg
setup.py
src/PyserSSH/__init__.py
src/PyserSSH/interactive.py
src/PyserSSH/server.py
src/PyserSSH.egg-info/PKG-INFO
src/PyserSSH.egg-info/SOURCES.txt
src/PyserSSH.egg-info/dependency_links.txt
src/PyserSSH.egg-info/requires.txt
src/PyserSSH.egg-info/top_level.txt
src/PyserSSH/account/AMInterface.py
src/PyserSSH/account/__init__.py
src/PyserSSH/account/localAM.py
src/PyserSSH/account/mongoAM.py
src/PyserSSH/extensions/AdvancedInput.py
src/PyserSSH/extensions/BarPlus.py
src/PyserSSH/extensions/STGL.py
src/PyserSSH/extensions/XHandler.py
src/PyserSSH/extensions/__init__.py
src/PyserSSH/extensions/dialog.py
src/PyserSSH/extensions/dialogplus.py
src/PyserSSH/extensions/keyInterrupter.py
src/PyserSSH/extensions/moredisplay.py
src/PyserSSH/extensions/moreinteractive.py
src/PyserSSH/extensions/processbar.py
src/PyserSSH/extensions/pyofetch.py
src/PyserSSH/extensions/remodesk.py
src/PyserSSH/extensions/serverutils.py
src/PyserSSH/extensions/virtualSTD.py
src/PyserSSH/system/KeyInteract.py
src/PyserSSH/system/RemoteStatus.py
src/PyserSSH/system/SFTP.py
src/PyserSSH/system/__init__.py
src/PyserSSH/system/clientype.py
src/PyserSSH/system/info.py
src/PyserSSH/system/inputsystem.py
src/PyserSSH/system/interface.py
src/PyserSSH/system/syscom.py
src/PyserSSH/system/sysfunc.py
src/PyserSSH/system/ProWrapper/PWInterface.py
src/PyserSSH/system/ProWrapper/SSHWrapper.py
src/PyserSSH/system/ProWrapper/TTYWrapper.py
src/PyserSSH/system/ProWrapper/TelnetWrapper.py
src/PyserSSH/system/ProWrapper/__init__.py
src/PyserSSH/utils/ServerManager.py
src/PyserSSH/utils/__init__.py
src/PyserSSH/utils/keygen.py