Metadata-Version: 2.2
Name: PyserSSH
Version: 6.0
Summary: python scriptable ssh server library. based on Paramiko
Home-page: https://github.com/damp11113/PyserSSH
Author: DPSoftware Foundation
Author-email: contact@damp11113.xyz
License: MIT
Keywords: SSH server
Classifier: Development Status :: 5 - Production/Stable
Classifier: License :: OSI Approved :: MIT License
Classifier: Intended Audience :: Developers
Classifier: Intended Audience :: System Administrators
Classifier: Operating System :: OS Independent
Classifier: Programming Language :: Python :: 3.10
Classifier: Topic :: Communications
Classifier: Topic :: Internet
Classifier: Topic :: Internet :: File Transfer Protocol (FTP)
Classifier: Topic :: Software Development
Classifier: Topic :: Terminals
Requires-Python: >=3.6
Requires-Dist: paramiko
Requires-Dist: psutil
Requires-Dist: pymongo
Provides-Extra: remodesk
Requires-Dist: mouse; extra == "remodesk"
Requires-Dist: keyboard; extra == "remodesk"
Requires-Dist: Brotli; extra == "remodesk"
Requires-Dist: pillow; extra == "remodesk"
Requires-Dist: numpy; extra == "remodesk"
Requires-Dist: opencv-python; extra == "remodesk"
Provides-Extra: ext-pyofetch
Requires-Dist: py-cpuinfo; extra == "ext-pyofetch"
Requires-Dist: GPUtil; extra == "ext-pyofetch"
Requires-Dist: distro; extra == "ext-pyofetch"
Dynamic: author
Dynamic: author-email
Dynamic: classifier
Dynamic: description
Dynamic: description-content-type
Dynamic: home-page
Dynamic: keywords
Dynamic: license
Dynamic: provides-extra
Dynamic: requires-dist
Dynamic: requires-python
Dynamic: summary
